workbooky/__init__.py
workbooky/_version.py
workbooky/src/__init__.py
workbooky/src/workbook.py
workbooky/tests/__init__.py
workbooky/tests/test_workbook.py
workbooky/tests/test_data/invalid_workbook.xlsx
workbooky/tests/test_data/valid_workbook.xlsx
workbooky-0.0.5.dist-info/LICENSE.txt
workbooky-0.0.5.dist-info/METADATA
workbooky-0.0.5.dist-info/WHEEL
workbooky-0.0.5.dist-info/top_level.txt
workbooky-0.0.5.dist-info/RECORD
