Metadata-Version: 2.1
Name: workbooky
Version: 0.0.5
Summary: """A collection of modules that supports workbooks with openpyxl."""
Home-page: https://psionman@bitbucket.org/psionman/workbooky.git
Download-URL: https://pypi.org/project/workbooky/
Author: jeff watkins
Author-email: support@bidforgame.com
License: MIT
Keywords: cli,input
License-File: LICENSE.txt
